refscan/__init__.py
refscan/cli/cli.py
refscan/cli/graph.py
refscan/cli/scan.py
refscan/cli/version.py
refscan/grapher.py
refscan/lib/Finder.py
refscan/lib/Reference.py
refscan/lib/ReferenceList.py
refscan/lib/Violation.py
refscan/lib/ViolationList.py
refscan/lib/constants.py
refscan/lib/helpers.py
refscan/scanner.py
refscan/templates/graph.template.html
refscan-0.4.3.dist-info/WHEEL
refscan-0.4.3.dist-info/entry_points.txt
refscan-0.4.3.dist-info/METADATA
refscan-0.4.3.dist-info/RECORD
