Metadata-Version: 2.3
Name: refscan
Version: 0.4.3
Summary: Command-line program that scans the NMDC MongoDB database for referential integrity violations
Keywords: mongodb,mongo,relationships,reference,database,data,referential integrity,scan
Requires-Dist: linkml-runtime>=1.7.5,<2
Requires-Dist: pymongo>=4.7.1,<5
Requires-Dist: rich>=13.7.1,<14
Requires-Dist: typer>=0.15.1,<0.16
Requires-Python: >=3.9, <4.0
Project-URL: Documentation, https://github.com/microbiomedata/refscan
Project-URL: Homepage, https://github.com/microbiomedata/refscan
Project-URL: Repository, https://github.com/microbiomedata/refscan
